pygrade/__init__.py
pygrade/cheat.py
pygrade/clone.py
pygrade/delete.py
pygrade/grade.py
pygrade/init.py
pygrade/push.py
pygrade/pygrade.py
pygrade/summarize.py
pygrade-0.2.5.dist-info/DESCRIPTION.rst
pygrade-0.2.5.dist-info/METADATA
pygrade-0.2.5.dist-info/RECORD
pygrade-0.2.5.dist-info/WHEEL
pygrade-0.2.5.dist-info/entry_points.txt
pygrade-0.2.5.dist-info/metadata.json
pygrade-0.2.5.dist-info/top_level.txt
