Metadata-Version: 2.0
Name: pygrade
Version: 0.2.5
Summary: auto-grade python assignments
Home-page: https://github.com/tapilab/pygrade
Author: Aron Culotta
Author-email: aronwc@gmail.com
License: ISCL
Keywords: pygrade
Platform: UNKNOWN
Classifier: Development Status :: 2 - Pre-Alpha
Classifier: Intended Audience :: Developers
Classifier: License :: OSI Approved :: ISC License (ISCL)
Classifier: Natural Language :: English
Classifier: Programming Language :: Python :: 2
Classifier: Programming Language :: Python :: 2.7
Classifier: Programming Language :: Python :: 3
Classifier: Programming Language :: Python :: 3.3
Classifier: Programming Language :: Python :: 3.4
Classifier: Programming Language :: Python :: 3.5
Requires-Dist: docopt
Requires-Dist: github3.py (>=1.0.0a4)
Requires-Dist: gitpython
Requires-Dist: nose
Requires-Dist: scikit-learn
Requires-Dist: wheel
